aaip/__init__.py
aaip/core/__init__.py
aaip/core/authorization.py
aaip/core/crypto.py
aaip/core/exceptions.py
aaip/core/identity.py
aaip-1.0.0.dist-info/METADATA
aaip-1.0.0.dist-info/WHEEL
aaip-1.0.0.dist-info/licenses/LICENSE
aaip-1.0.0.dist-info/RECORD
