Metadata-Version: 2.4
Name: aaip
Version: 1.0.0
Summary: AI Agent Identity Protocol (AAIP) - Standard delegation format for AI agent authorization
Project-URL: Homepage, https://github.com/krisdiallo/aaip-spec
Project-URL: Repository, https://github.com/krisdiallo/aaip-spec
Project-URL: Issues, https://github.com/krisdiallo/aaip-spec/issues
Project-URL: Changelog, https://github.com/krisdiallo/aaip-spec/blob/main/CHANGELOG.md
Author: Kris Diallo
Maintainer: Kris Diallo
License:                                  Apache License
License-File: LICENSE
Keywords: agents,ai,authorization,delegation,identity,protocol
Classifier: Development Status :: 4 - Beta
Classifier: Intended Audience :: Developers
Classifier: License :: OSI Approved :: Apache Software License
Classifier: Operating System :: OS Independent
Classifier: Programming Language :: Python :: 3
Classifier: Programming Language :: Python :: 3.9
Classifier: Programming Language :: Python :: 3.10
Classifier: Programming Language :: Python :: 3.11
Classifier: Programming Language :: Python :: 3.12
Classifier: Topic :: Security
Classifier: Topic :: Software Development :: Libraries :: Python Modules
Classifier: Topic :: System :: Distributed Computing
Requires-Python: >=3.9
Requires-Dist: cryptography>=41.0.0
Provides-Extra: dev
Requires-Dist: black>=23.0.0; extra == 'dev'
Requires-Dist: build>=0.10.0; extra == 'dev'
Requires-Dist: mypy>=1.0.0; extra == 'dev'
Requires-Dist: pytest-asyncio>=0.21.0; extra == 'dev'
Requires-Dist: pytest-cov>=4.0.0; extra == 'dev'
Requires-Dist: pytest>=7.0.0; extra == 'dev'
Requires-Dist: ruff>=0.1.0; extra == 'dev'
Requires-Dist: twine>=4.0.0; extra == 'dev'
Provides-Extra: examples
Requires-Dist: fastapi>=0.100.0; extra == 'examples'
Requires-Dist: langchain-core>=0.1.0; extra == 'examples'
Requires-Dist: langchain-openai>=0.1.0; extra == 'examples'
Requires-Dist: langchain>=0.1.0; extra == 'examples'
Requires-Dist: uvicorn[standard]>=0.22.0; extra == 'examples'
Provides-Extra: test
Requires-Dist: pytest-asyncio>=0.21.0; extra == 'test'
Requires-Dist: pytest-cov>=4.0.0; extra == 'test'
Requires-Dist: pytest>=7.0.0; extra == 'test'
